{
  "accounts": [
    {
      "id": 1,
      "first_name": "Britney",
      "last_name": "Rafer",
      "email": "britney.rafer@gmail.com",
      "password":"$2y$12$pkgLgVh8QKaRk9Q4is5AWu1K1jFesLTdyFxGym.OBe1KF7ZDf4jc.",
      "image": "images/accounts/1.png"
    },
    {
      "id": 2,
      "first_name": "Mariel",
      "last_name": "Perin",
      "email": "mariel.perin@gmail.com",
      "password":"$2y$12$pkgLgVh8QKaRk9Q4is5AWu1K1jFesLTdyFxGym.OBe1KF7ZDf4jc.",
      "image": "images/accounts/2.png"
    },
    {
      "id": 3,
      "first_name": "Izzy",
      "last_name": "DeJusto",
      "email": "izzy.dejusto@gmail.com",
      "password": "$2y$12$pkgLgVh8QKaRk9Q4is5AWu1K1jFesLTdyFxGym.OBe1KF7ZDf4jc.",
      "image": "images/accounts/3.png"
    },
    {
      "id": 4,
      "first_name": "Francis Luis",
      "last_name": "Rances",
      "email": "francis.rances@gmail.com",
      "password": "$2y$12$pkgLgVh8QKaRk9Q4is5AWu1K1jFesLTdyFxGym.OBe1KF7ZDf4jc.",
      "image": "images/accounts/4.png"
    },
    {
      "id": 5,
      "first_name": "Angelito",
      "last_name": "Guiaya",
      "email": "angelito.guiaya@gmail.com",
      "password": "$2y$12$pkgLgVh8QKaRk9Q4is5AWu1K1jFesLTdyFxGym.OBe1KF7ZDf4jc.",
      "image": "images/accounts/5.png"
    }
  ],
  "payment_details": [
    {
      "id": 1,
      "account_id": 1,
      "recipient_name": "Britney Rafer",
      "phone_number": "09171234567",
      "district": "Ugong",
      "city": "Pasig City",
      "region": "NCR",
      "street": "88 Arcovia Ave",
      "address_category": "home address"
    },
    {
      "id": 2,
      "account_id": 2,
      "recipient_name": "Mariel Perin",
      "phone_number": "09181234567",
      "district": "San Miguel",
      "city": "Manila",
      "region": "NCR",
      "street": "456 General Luna St",
      "address_category": "office address"
    },
    {
      "id": 3,
      "account_id": 3,
      "recipient_name": "Izzy DeJusto",
      "phone_number": "09221234567",
      "district": "Poblacion",
      "city": "Makati",
      "region": "NCR",
      "street": "789 Kalayaan Ave",
      "address_category": "home address"
    },
    {
      "id": 4,
      "account_id": 4,
      "recipient_name": "Francis Luis Rances",
      "phone_number": "09091234567",
      "district": "Buli",
      "city": "Muntinlupa",
      "region": "NCR",
      "street": "101 Civic Drive",
      "address_category": "office address"
    },
    {
      "id": 5,
      "account_id": 5,
      "recipient_name": "Angelito Guiaya",
      "phone_number": "09391234567",
      "district": "San Roque",
      "city": "Marikina",
      "region": "NCR",
      "street": "123 Shoe Ave",
      "address_category": "home address"
    }
  ],
"user_profilings": [
  {
    "id": 1,
    "account_id": 1,
    "birthdate": "2003-05-15",
    "sex": "Female",
    "height": 160.5,
    "weight": 55.2,
    "activity_type": "[\"Leisure\", \"Commuting\"]",
    "terrain": "[\"Mixed\"]",
    "experience_level": "Intermediate",
    "maintenance": 0,
    "custom_parts": 1,
    "created_at": null,
    "updated_at": null
  },
  {
    "id": 2,
    "account_id": 2,
    "birthdate": "2002-11-22",
    "sex": "Female",
    "height": 162,
    "weight": 50.8,
    "activity_type": "[\"Commuting\", \"Touring\"]",
    "terrain": "[\"Coastal Roads\"]",
    "experience_level": "Beginner",
    "maintenance": 1,
    "custom_parts": 1,
    "created_at": null,
    "updated_at": null
  },
  {
    "id": 3,
    "account_id": 3,
    "birthdate": "2003-02-10",
    "sex": "Female",
    "height": 158.3,
    "weight": 53,
    "activity_type": "[\"Off-roading\", \"Racing\"]",
    "terrain": "[\"Mountains\"]",
    "experience_level": "Advanced",
    "maintenance": 0,
    "custom_parts": 0,
    "created_at": null,
    "updated_at": null
  },
  {
    "id": 4,
    "account_id": 4,
    "birthdate": "2002-08-05",
    "sex": "Male",
    "height": 175.7,
    "weight": 68.5,
    "activity_type": "[\"Racing\", \"Touring\"]",
    "terrain": "[\"Mountains\", \"Mixed\"]",
    "experience_level": "Advanced",
    "maintenance": 1,
    "custom_parts": 1,
    "created_at": null,
    "updated_at": null
  },
  {
    "id": 5,
    "account_id": 5,
    "birthdate": "2003-07-30",
    "sex": "Male",
    "height": 170,
    "weight": 63.4,
    "activity_type": "[\"Touring\", \"Leisure\"]",
    "terrain": "[\"Mixed\"]",
    "experience_level": "Advanced",
    "maintenance": 0,
    "custom_parts": 0,
    "created_at": null,
    "updated_at": null
  }
],
"orders": [
  {
    "id": 1,
    "product_id": 1,
    "account_id": 1,
    "quantity": 2,
    "order_status": "Completed",
    "created_at": "2024-01-05",
    "updated_at": "2024-01-05"
  },
  {
    "id": 2,
    "product_id": 2,
    "account_id": 2,
    "quantity": 1,
    "order_status": "Completed",
    "created_at": "2024-01-12",
    "updated_at": "2024-01-12"
  },
  {
    "id": 3,
    "product_id": 3,
    "account_id": 3,
    "quantity": 3,
    "order_status": "Completed",
    "created_at": "2024-01-19",
    "updated_at": "2024-01-19"
  },
  {
    "id": 4,
    "product_id": 4,
    "account_id": 4,
    "quantity": 2,
    "order_status": "Completed",
    "created_at": "2024-02-01",
    "updated_at": "2024-02-01"
  },
  {
    "id": 5,
    "product_id": 5,
    "account_id": 5,
    "quantity": 4,
    "order_status": "Completed",
    "created_at": "2024-02-10",
    "updated_at": "2024-02-10"
  },
  {
    "id": 6,
    "product_id": 6,
    "account_id": 1,
    "quantity": 5,
    "order_status": "Completed",
    "created_at": "2024-02-18",
    "updated_at": "2024-02-18"
  },
  {
    "id": 7,
    "product_id": 7,
    "account_id": 2,
    "quantity": 1,
    "order_status": "Completed",
    "created_at": "2024-03-02",
    "updated_at": "2024-03-02"
  },
  {
    "id": 8,
    "product_id": 8,
    "account_id": 3,
    "quantity": 2,
    "order_status": "Completed",
    "created_at": "2024-03-08",
    "updated_at": "2024-03-08"
  },
  {
    "id": 9,
    "product_id": 9,
    "account_id": 4,
    "quantity": 3,
    "order_status": "Completed",
    "created_at": "2024-03-16",
    "updated_at": "2024-03-16"
  },
  {
    "id": 10,
    "product_id": 10,
    "account_id": 5,
    "quantity": 1,
    "order_status": "Completed",
    "created_at": "2024-03-22",
    "updated_at": "2024-03-22"
  },
  {
    "id": 11,
    "product_id": 11,
    "account_id": 1,
    "quantity": 2,
    "order_status": "To receive",
    "created_at": "2024-04-01",
    "updated_at": "2024-04-01"
  },
  {
    "id": 12,
    "product_id": 12,
    "account_id": 2,
    "quantity": 1,
    "order_status": "To receive",
    "created_at": "2024-04-07",
    "updated_at": "2024-04-07"
  },
  {
    "id": 13,
    "product_id": 13,
    "account_id": 3,
    "quantity": 3,
    "order_status": "To receive",
    "created_at": "2024-04-13",
    "updated_at": "2024-04-13"
  },
  {
    "id": 14,
    "product_id": 14,
    "account_id": 4,
    "quantity": 2,
    "order_status": "To receive",
    "created_at": "2024-04-21",
    "updated_at": "2024-04-21"
  },
  {
    "id": 15,
    "product_id": 15,
    "account_id": 5,
    "quantity": 4,
    "order_status": "To receive",
    "created_at": "2024-04-30",
    "updated_at": "2024-04-30"
  },
  {
    "id": 16,
    "product_id": 16,
    "account_id": 1,
    "quantity": 5,
    "order_status": "To ship",
    "created_at": "2024-05-06",
    "updated_at": "2024-05-06"
  },
  {
    "id": 17,
    "product_id": 17,
    "account_id": 2,
    "quantity": 1,
    "order_status": "To ship",
    "created_at": "2024-05-12",
    "updated_at": "2024-05-12"
  },
  {
    "id": 18,
    "product_id": 18,
    "account_id": 3,
    "quantity": 2,
    "order_status": "To ship",
    "created_at": "2024-05-18",
    "updated_at": "2024-05-18"
  },
  {
    "id": 19,
    "product_id": 19,
    "account_id": 4,
    "quantity": 3,
    "order_status": "To ship",
    "created_at": "2024-05-24",
    "updated_at": "2024-05-24"
  },
  {
    "id": 20,
    "product_id": 20,
    "account_id": 5,
    "quantity": 1,
    "order_status": "To ship",
    "created_at": "2024-06-01",
    "updated_at": "2024-06-01"
  },
  {
    "id": 21,
    "product_id": 21,
    "account_id": 1,
    "quantity": 2,
    "order_status": "Cancelled",
    "created_at": "2024-06-06",
    "updated_at": "2024-06-06"
  },
  {
    "id": 22,
    "product_id": 22,
    "account_id": 2,
    "quantity": 1,
    "order_status": "Cancelled",
    "created_at": "2024-06-10",
    "updated_at": "2024-06-10"
  },
  {
    "id": 23,
    "product_id": 23,
    "account_id": 3,
    "quantity": 3,
    "order_status": "Cancelled",
    "created_at": "2024-06-14",
    "updated_at": "2024-06-14"
  },
  {
    "id": 24,
    "product_id": 24,
    "account_id": 4,
    "quantity": 2,
    "order_status": "Cancelled",
    "created_at": "2024-06-18",
    "updated_at": "2024-06-18"
  },
  {
    "id": 25,
    "product_id": 25,
    "account_id": 5,
    "quantity": 4,
    "order_status": "Cancelled",
    "created_at": "2024-06-22",
    "updated_at": "2024-06-22"
  },
  {
    "id": 26,
    "product_id": 26,
    "account_id": 1,
    "quantity": 5,
    "order_status": "To receive",
    "created_at": "2024-06-26",
    "updated_at": "2024-06-26"
  },
  {
    "id": 27,
    "product_id": 27,
    "account_id": 2,
    "quantity": 1,
    "order_status": "To receive",
    "created_at": "2024-06-30",
    "updated_at": "2024-06-30"
  },
  {
    "id": 28,
    "product_id": 28,
    "account_id": 3,
    "quantity": 2,
    "order_status": "To receive",
    "created_at": "2024-07-03",
    "updated_at": "2024-07-03"
  },
  {
    "id": 29,
    "product_id": 29,
    "account_id": 4,
    "quantity": 3,
    "order_status": "To receive",
    "created_at": "2024-07-06",
    "updated_at": "2024-07-06"
  },
  {
    "id": 30,
    "product_id": 30,
    "account_id": 5,
    "quantity": 1,
    "order_status": "To receive",
    "created_at": "2024-07-10",
    "updated_at": "2024-07-10"
  },
  {
    "id": 31,
    "product_id": 31,
    "account_id": 1,
    "quantity": 2,
    "order_status": "To ship",
    "created_at": "2024-07-15",
    "updated_at": "2024-07-15"
  },
  {
    "id": 32,
    "product_id": 32,
    "account_id": 2,
    "quantity": 1,
    "order_status": "To ship",
    "created_at": "2024-07-20",
    "updated_at": "2024-07-20"
  },
  {
    "id": 33,
    "product_id": 33,
    "account_id": 3,
    "quantity": 3,
    "order_status": "To ship",
    "created_at": "2024-07-25",
    "updated_at": "2024-07-25"
  },
  {
    "id": 34,
    "product_id": 34,
    "account_id": 4,
    "quantity": 2,
    "order_status": "To ship",
    "created_at": "2024-07-30",
    "updated_at": "2024-07-30"
  },
  {
    "id": 35,
    "product_id": 35,
    "account_id": 5,
    "quantity": 4,
    "order_status": "To ship",
    "created_at": "2024-08-04",
    "updated_at": "2024-08-04"
  },
  {
    "id": 36,
    "product_id": 36,
    "account_id": 1,
    "quantity": 5,
    "order_status": "Refunded",
    "created_at": "2024-08-09",
    "updated_at": "2024-08-09"
  },
  {
    "id": 37,
    "product_id": 37,
    "account_id": 2,
    "quantity": 1,
    "order_status": "Refunded",
    "created_at": "2024-08-14",
    "updated_at": "2024-08-14"
  },
  {
    "id": 38,
    "product_id": 38,
    "account_id": 3,
    "quantity": 2,
    "order_status": "Refunded",
    "created_at": "2024-08-19",
    "updated_at": "2024-08-19"
  },
  {
    "id": 39,
    "product_id": 39,
    "account_id": 4,
    "quantity": 3,
    "order_status": "Refunded",
    "created_at": "2024-08-24",
    "updated_at": "2024-08-24"
  },
  {
    "id": 40,
    "product_id": 40,
    "account_id": 5,
    "quantity": 1,
    "order_status": "Refunded",
    "created_at": "2024-08-29",
    "updated_at": "2024-08-29"
  }
],

"carts": [
  {
    "id": 1,
    "product_id": 1,
    "account_id": 1,
    "quantity": 1,
    "created_at": null,
    "updated_at": null
  },
  {
    "id": 2,
    "product_id": 2,
    "account_id": 2,
    "quantity": 1,
    "created_at": null,
    "updated_at": null
  }
],
"wishlists": [
  {
    "id": 1,
    "product_id": 1,
    "account_id": 1,
    "created_at": null,
    "updated_at": null
  },
  {
    "id": 2,
    "product_id": 2,
    "account_id": 2,
    "created_at": null,
    "updated_at": null
  }
]
} 
